mysql_to_sheets/__init__.py
mysql_to_sheets/__main__.py
mysql_to_sheets/py.typed
mysql_to_sheets/agent/__init__.py
mysql_to_sheets/agent/__main__.py
mysql_to_sheets/agent/agent_worker.py
mysql_to_sheets/agent/crash_handler.py
mysql_to_sheets/agent/link_config_provider.py
mysql_to_sheets/agent/link_token.py
mysql_to_sheets/agent/updater.py
mysql_to_sheets/api/__init__.py
mysql_to_sheets/api/app.py
mysql_to_sheets/api/audit_routes.py
mysql_to_sheets/api/auth_routes.py
mysql_to_sheets/api/billing_webhook_routes.py
mysql_to_sheets/api/config_routes.py
mysql_to_sheets/api/freshness_routes.py
mysql_to_sheets/api/job_routes.py
mysql_to_sheets/api/metrics_routes.py
mysql_to_sheets/api/responses.py
mysql_to_sheets/api/rollback_routes.py
mysql_to_sheets/api/routes.py
mysql_to_sheets/api/routes_agent.py
mysql_to_sheets/api/routes_pii.py
mysql_to_sheets/api/schemas.py
mysql_to_sheets/api/usage_routes.py
mysql_to_sheets/api/user_routes.py
mysql_to_sheets/api/webhook_routes.py
mysql_to_sheets/api/middleware/__init__.py
mysql_to_sheets/api/middleware/audit.py
mysql_to_sheets/api/middleware/auth.py
mysql_to_sheets/api/middleware/cors.py
mysql_to_sheets/api/middleware/dependencies.py
mysql_to_sheets/api/middleware/https.py
mysql_to_sheets/api/middleware/organization.py
mysql_to_sheets/api/middleware/rate_limit.py
mysql_to_sheets/api/middleware/rbac.py
mysql_to_sheets/api/middleware/request_size.py
mysql_to_sheets/api/middleware/scope.py
mysql_to_sheets/api/middleware/tier.py
mysql_to_sheets/api/middleware/tracking.py
mysql_to_sheets/api/middleware/user_auth.py
mysql_to_sheets/cli/__init__.py
mysql_to_sheets/cli/admin_commands.py
mysql_to_sheets/cli/api_key_commands.py
mysql_to_sheets/cli/audit_commands.py
mysql_to_sheets/cli/config_commands.py
mysql_to_sheets/cli/db_commands.py
mysql_to_sheets/cli/diagnose_commands.py
mysql_to_sheets/cli/favorite_commands.py
mysql_to_sheets/cli/freshness_commands.py
mysql_to_sheets/cli/history_commands.py
mysql_to_sheets/cli/job_commands.py
mysql_to_sheets-1.0.0.dist-info/licenses/LICENSE
mysql_to_sheets-1.0.0.dist-info/METADATA
mysql_to_sheets-1.0.0.dist-info/WHEEL
mysql_to_sheets-1.0.0.dist-info/entry_points.txt
mysql_to_sheets-1.0.0.dist-info/top_level.txt
mysql_to_sheets-1.0.0.dist-info/RECORD
