Metadata-Version: 2.4
Name: mysql-to-sheets
Version: 1.0.0
Summary: Sync MySQL/PostgreSQL/SQLite/MSSQL data to Google Sheets with CLI, API, and Web Dashboard
Author-email: Texas Longhorn Analytics <frickesoftware@gmail.com>
License: MIT
Project-URL: Homepage, https://github.com/BrandonFricke/mysql-to-sheets
Project-URL: Documentation, https://github.com/BrandonFricke/mysql-to-sheets#readme
Project-URL: Repository, https://github.com/BrandonFricke/mysql-to-sheets
Project-URL: Issues, https://github.com/BrandonFricke/mysql-to-sheets/issues
Project-URL: Changelog, https://github.com/BrandonFricke/mysql-to-sheets/blob/main/CHANGELOG.md
Keywords: mysql,google-sheets,sync,etl,data-pipeline,postgresql,sqlite,mssql,sql-server,spreadsheet,automation,data-export
Classifier: Development Status :: 5 - Production/Stable
Classifier: Environment :: Console
Classifier: Environment :: Web Environment
Classifier: Framework :: FastAPI
Classifier: Framework :: Flask
Classifier: Intended Audience :: Developers
Classifier: Intended Audience :: System Administrators
Classifier: License :: OSI Approved :: MIT License
Classifier: Operating System :: OS Independent
Classifier: Programming Language :: Python :: 3
Classifier: Programming Language :: Python :: 3.10
Classifier: Programming Language :: Python :: 3.11
Classifier: Programming Language :: Python :: 3.12
Classifier: Programming Language :: Python :: 3.13
Classifier: Topic :: Database
Classifier: Topic :: Database :: Front-Ends
Classifier: Topic :: Internet :: WWW/HTTP :: WSGI :: Application
Classifier: Topic :: Office/Business :: Office Suites
Classifier: Typing :: Typed
Requires-Python: >=3.10
License-File: LICENSE
Requires-Dist: gspread~=6.1.2
Requires-Dist: google-auth~=2.23.0
Requires-Dist: mysql-connector-python~=9.0.0
Requires-Dist: python-dotenv~=1.0.1
Requires-Dist: fastapi~=0.109.0
Requires-Dist: uvicorn~=0.27.0
Requires-Dist: pydantic~=2.5.3
Requires-Dist: flask~=3.0.0
Requires-Dist: flask-wtf~=1.2.1
Requires-Dist: sqlalchemy~=2.0.25
Requires-Dist: alembic~=1.13.0
Requires-Dist: APScheduler~=3.10.4
Requires-Dist: bcrypt~=4.0.0
Requires-Dist: PyJWT~=2.8.0
Requires-Dist: PyYAML~=6.0
Requires-Dist: cryptography>=42.0
Provides-Extra: postgres
Requires-Dist: psycopg2-binary~=2.9.9; extra == "postgres"
Provides-Extra: mssql
Requires-Dist: pymssql~=2.2.0; extra == "mssql"
Provides-Extra: redis
Requires-Dist: redis~=5.0.0; extra == "redis"
Provides-Extra: desktop
Requires-Dist: pystray>=0.19.0; extra == "desktop"
Requires-Dist: plyer>=2.1.0; extra == "desktop"
Requires-Dist: Pillow>=10.0.0; extra == "desktop"
Requires-Dist: pywebview>=5.0; extra == "desktop"
Requires-Dist: keyring>=25.0; extra == "desktop"
Requires-Dist: ttkbootstrap>=1.10; extra == "desktop"
Provides-Extra: all
Requires-Dist: psycopg2-binary~=2.9.9; extra == "all"
Requires-Dist: pymssql~=2.2.0; extra == "all"
Requires-Dist: redis~=5.0.0; extra == "all"
Requires-Dist: pystray>=0.19.0; extra == "all"
Requires-Dist: plyer>=2.1.0; extra == "all"
Requires-Dist: Pillow>=10.0.0; extra == "all"
Requires-Dist: pywebview>=5.0; extra == "all"
Requires-Dist: keyring>=25.0; extra == "all"
Requires-Dist: ttkbootstrap>=1.10; extra == "all"
Provides-Extra: dev
Requires-Dist: pytest>=7.4.0; extra == "dev"
Requires-Dist: pytest-cov>=4.1.0; extra == "dev"
Requires-Dist: pytest-asyncio>=0.21.0; extra == "dev"
Requires-Dist: pytest-xdist>=3.5.0; extra == "dev"
Requires-Dist: freezegun>=1.2.0; extra == "dev"
Requires-Dist: httpx>=0.25.0; extra == "dev"
Requires-Dist: mypy>=1.7.0; extra == "dev"
Requires-Dist: ruff>=0.1.0; extra == "dev"
Requires-Dist: fakeredis>=2.21.0; extra == "dev"
Provides-Extra: build
Requires-Dist: pyinstaller>=6.0.0; extra == "build"
Dynamic: license-file
